Mobel/__init__.py
Mobel/annotation.py
Mobel/common.py
Mobel/decorator.py
Mobel/pipe.py
mobel-0.3.1.dist-info/LICENSE
mobel-0.3.1.dist-info/METADATA
mobel-0.3.1.dist-info/WHEEL
mobel-0.3.1.dist-info/top_level.txt
mobel-0.3.1.dist-info/RECORD
