Metadata-Version: 2.1
Name: mobel
Version: 0.3.1
Summary: improved decorator support
Home-page: https://github.com/youssef-jbili/mobel
Author: youssefj
Author-email: jbili.jbili.youssef@gmail.com
License: MIT License
Project-URL: Bug Tracker, https://github.com/youssef-jbili/mobel/issues
Platform: UNKNOWN
Classifier: Programming Language :: Python :: 3
Classifier: License :: OSI Approved :: MIT License
Classifier: Operating System :: OS Independent
Requires-Python: >=3.8
License-File: LICENSE
